iglu/__init__.py
iglu/const.py
iglu/env.py
iglu/handlers.py
iglu/tasks/__init__.py
iglu/tasks/load.py
iglu/tasks/task.py
iglu/tasks/task_names.txt
iglu/tasks/task_set.py
iglu-0.2.2.dist-info/METADATA
iglu-0.2.2.dist-info/WHEEL
iglu-0.2.2.dist-info/top_level.txt
iglu-0.2.2.dist-info/RECORD
